[
   {
      "id": 1,
      "name": "Ferrari",
      "cars": [
         {
            "id": 1,
            "decade": "1950s",
            "name": "250 Testa Rossa",
            "img": "url(src/assets/ferrari/1950s.jpg)",
            "desc": "Lorem ipsum",
            "top": 350,
            "hp": 530,
            "acc": 5.4
         },
         {
            "id": 2,
            "decade": "1960s",
            "name": "250 GTO",
            "img": "url(src/assets/ferrari/1960s.jpg)",
            "desc": "Lorem ipsum",
            "top": 350,
            "hp": 530,
            "acc": 5.4
         },
         {
            "id": 3,
            "decade": "1970s",
            "name": "308 GTB",
            "img": "url(src/assets/ferrari/1970s.jpg)",
            "desc": "Lorem ipsum",
            "top": 350,
            "hp": 530,
            "acc": 5.4
         },
         {
            "id": 4,
            "decade": "1980s",
            "name": "F40",
            "img": "url(src/assets/ferrari/1980s.jpg)",
            "desc": "Lorem ipsum",
            "top": 350,
            "hp": 530,
            "acc": 5.4
         },
         {
            "id": 5,
            "decade": "1990s",
            "name": "F355",
            "img": "url(src/assets/ferrari/1990s.jpg)",
            "desc": "Lorem ipsum",
            "top": 350,
            "hp": 530,
            "acc": 5.4
         },
         {
            "id": 6,
            "decade": "2000s",
            "name": "Enzo",
            "img": "url(src/assets/ferrari/2000s.jpg)",
            "desc": "Lorem ipsum",
            "top": 350,
            "hp": 530,
            "acc": 5.4
         },
         {
            "id": 7,
            "decade": "2010s",
            "name": "LaFerrari",
            "img": "url(src/assets/ferrari/2010s.jpg)",
            "desc": "Lorem ipsum",
            "top": 350,
            "hp": 530,
            "acc": 5.4
         }
      ]
   },
   {
      "id": 2,
      "name": "Porsche",
      "cars": [
         {
            "id": 1,
            "decade": "1950s",
            "name": "250 Testa Rossa",
            "img": "url(src/assets/ferrari/1950s.jpg)",
            "desc": "Lorem ipsum",
            "top": 350,
            "hp": 530,
            "acc": 5.4
         },
         {
            "id": 2,
            "decade": "1960s",
            "name": "250 GTO",
            "img": "url(src/assets/ferrari/1960s.jpg)",
            "desc": "Lorem ipsum",
            "top": 350,
            "hp": 530,
            "acc": 5.4
         },
         {
            "id": 3,
            "decade": "1970s",
            "name": "308 GTB",
            "img": "url(src/assets/ferrari/1970s.jpg)",
            "desc": "Lorem ipsum",
            "top": 350,
            "hp": 530,
            "acc": 5.4
         },
         {
            "id": 4,
            "decade": "1980s",
            "name": "F40",
            "img": "url(src/assets/ferrari/1980s.jpg)",
            "desc": "Lorem ipsum",
            "top": 350,
            "hp": 530,
            "acc": 5.4
         },
         {
            "id": 5,
            "decade": "1990s",
            "name": "F355",
            "img": "url(src/assets/ferrari/1990s.jpg)",
            "desc": "Lorem ipsum",
            "top": 350,
            "hp": 530,
            "acc": 5.4
         },
         {
            "id": 6,
            "decade": "2000s",
            "name": "Enzo",
            "img": "url(src/assets/ferrari/2000s.jpg)",
            "desc": "Lorem ipsum",
            "top": 350,
            "hp": 530,
            "acc": 5.4
         },
         {
            "id": 7,
            "decade": "2010s",
            "name": "LaFerrari",
            "img": "url(src/assets/ferrari/2010s.jpg)",
            "desc": "Lorem ipsum",
            "top": 350,
            "hp": 530,
            "acc": 5.4
         }
      ]
   },
   {
      "id": 3,
      "name": "Lamborghini",
      "cars": [
         {
            "id": 1,
            "decade": "1950s",
            "name": "250 Testa Rossa",
            "img": "url(src/assets/ferrari/1950s.jpg)",
            "desc": "Lorem ipsum",
            "top": 350,
            "hp": 530,
            "acc": 5.4
         },
         {
            "id": 2,
            "decade": "1960s",
            "name": "250 GTO",
            "img": "url(src/assets/ferrari/1960s.jpg)",
            "desc": "Lorem ipsum",
            "top": 350,
            "hp": 530,
            "acc": 5.4
         },
         {
            "id": 3,
            "decade": "1970s",
            "name": "308 GTB",
            "img": "url(src/assets/ferrari/1970s.jpg)",
            "desc": "Lorem ipsum",
            "top": 350,
            "hp": 530,
            "acc": 5.4
         },
         {
            "id": 4,
            "decade": "1980s",
            "name": "F40",
            "img": "url(src/assets/ferrari/1980s.jpg)",
            "desc": "Lorem ipsum",
            "top": 350,
            "hp": 530,
            "acc": 5.4
         },
         {
            "id": 5,
            "decade": "1990s",
            "name": "F355",
            "img": "url(src/assets/ferrari/1990s.jpg)",
            "desc": "Lorem ipsum",
            "top": 350,
            "hp": 530,
            "acc": 5.4
         },
         {
            "id": 6,
            "decade": "2000s",
            "name": "Enzo",
            "img": "url(src/assets/ferrari/2000s.jpg)",
            "desc": "Lorem ipsum",
            "top": 350,
            "hp": 530,
            "acc": 5.4
         },
         {
            "id": 7,
            "decade": "2010s",
            "name": "LaFerrari",
            "img": "url(src/assets/ferrari/2010s.jpg)",
            "desc": "Lorem ipsum",
            "top": 350,
            "hp": 530,
            "acc": 5.4
         }
      ]
   },
   {
      "id": 4,
      "name": "Volvo",
      "cars": [
         {
            "id": 1,
            "decade": "1950s",
            "name": "250 Testa Rossa",
            "img": "url(src/assets/ferrari/1950s.jpg)",
            "desc": "Lorem ipsum",
            "top": 350,
            "hp": 530,
            "acc": 5.4
         },
         {
            "id": 2,
            "decade": "1960s",
            "name": "250 GTO",
            "img": "url(src/assets/ferrari/1960s.jpg)",
            "desc": "Lorem ipsum",
            "top": 350,
            "hp": 530,
            "acc": 5.4
         },
         {
            "id": 3,
            "decade": "1970s",
            "name": "308 GTB",
            "img": "url(src/assets/ferrari/1970s.jpg)",
            "desc": "Lorem ipsum",
            "top": 350,
            "hp": 530,
            "acc": 5.4
         },
         {
            "id": 4,
            "decade": "1980s",
            "name": "F40",
            "img": "url(src/assets/ferrari/1980s.jpg)",
            "desc": "Lorem ipsum",
            "top": 350,
            "hp": 530,
            "acc": 5.4
         },
         {
            "id": 5,
            "decade": "1990s",
            "name": "F355",
            "img": "url(src/assets/ferrari/1990s.jpg)",
            "desc": "Lorem ipsum",
            "top": 350,
            "hp": 530,
            "acc": 5.4
         },
         {
            "id": 6,
            "decade": "2000s",
            "name": "Enzo",
            "img": "url(src/assets/ferrari/2000s.jpg)",
            "desc": "Lorem ipsum",
            "top": 350,
            "hp": 530,
            "acc": 5.4
         },
         {
            "id": 7,
            "decade": "2010s",
            "name": "LaFerrari",
            "img": "url(src/assets/ferrari/2010s.jpg)",
            "desc": "Lorem ipsum",
            "top": 350,
            "hp": 530,
            "acc": 5.4
         }
      ]
   },
   {
      "id": 5,
      "name": "McLaren",
      "cars": [
         {
            "id": 1,
            "decade": "1950s",
            "name": "250 Testa Rossa",
            "img": "url(src/assets/ferrari/1950s.jpg)",
            "desc": "Lorem ipsum",
            "top": 350,
            "hp": 530,
            "acc": 5.4
         },
         {
            "id": 2,
            "decade": "1960s",
            "name": "250 GTO",
            "img": "url(src/assets/ferrari/1960s.jpg)",
            "desc": "Lorem ipsum",
            "top": 350,
            "hp": 530,
            "acc": 5.4
         },
         {
            "id": 3,
            "decade": "1970s",
            "name": "308 GTB",
            "img": "url(src/assets/ferrari/1970s.jpg)",
            "desc": "Lorem ipsum",
            "top": 350,
            "hp": 530,
            "acc": 5.4
         },
         {
            "id": 4,
            "decade": "1980s",
            "name": "F40",
            "img": "url(src/assets/ferrari/1980s.jpg)",
            "desc": "Lorem ipsum",
            "top": 350,
            "hp": 530,
            "acc": 5.4
         },
         {
            "id": 5,
            "decade": "1990s",
            "name": "F355",
            "img": "url(src/assets/ferrari/1990s.jpg)",
            "desc": "Lorem ipsum",
            "top": 350,
            "hp": 530,
            "acc": 5.4
         },
         {
            "id": 6,
            "decade": "2000s",
            "name": "Enzo",
            "img": "url(src/assets/ferrari/2000s.jpg)",
            "desc": "Lorem ipsum",
            "top": 350,
            "hp": 530,
            "acc": 5.4
         },
         {
            "id": 7,
            "decade": "2010s",
            "name": "LaFerrari",
            "img": "url(src/assets/ferrari/2010s.jpg)",
            "desc": "Lorem ipsum",
            "top": 350,
            "hp": 530,
            "acc": 5.4
         }
      ]
   },
   {
      "id": 6,
      "name": "Renault",
      "cars": [
         {
            "id": 1,
            "decade": "1950s",
            "name": "250 Testa Rossa",
            "img": "url(src/assets/ferrari/1950s.jpg)",
            "desc": "Lorem ipsum",
            "top": 350,
            "hp": 530,
            "acc": 5.4
         },
         {
            "id": 2,
            "decade": "1960s",
            "name": "250 GTO",
            "img": "url(src/assets/ferrari/1960s.jpg)",
            "desc": "Lorem ipsum",
            "top": 350,
            "hp": 530,
            "acc": 5.4
         },
         {
            "id": 3,
            "decade": "1970s",
            "name": "308 GTB",
            "img": "url(src/assets/ferrari/1970s.jpg)",
            "desc": "Lorem ipsum",
            "top": 350,
            "hp": 530,
            "acc": 5.4
         },
         {
            "id": 4,
            "decade": "1980s",
            "name": "F40",
            "img": "url(src/assets/ferrari/1980s.jpg)",
            "desc": "Lorem ipsum",
            "top": 350,
            "hp": 530,
            "acc": 5.4
         },
         {
            "id": 5,
            "decade": "1990s",
            "name": "F355",
            "img": "url(src/assets/ferrari/1990s.jpg)",
            "desc": "Lorem ipsum",
            "top": 350,
            "hp": 530,
            "acc": 5.4
         },
         {
            "id": 6,
            "decade": "2000s",
            "name": "Enzo",
            "img": "url(src/assets/ferrari/2000s.jpg)",
            "desc": "Lorem ipsum",
            "top": 350,
            "hp": 530,
            "acc": 5.4
         },
         {
            "id": 7,
            "decade": "2010s",
            "name": "LaFerrari",
            "img": "url(src/assets/ferrari/2010s.jpg)",
            "desc": "Lorem ipsum",
            "top": 350,
            "hp": 530,
            "acc": 5.4
         }
      ]
   }
]
